tcp_modbus_aio/__init__.py
tcp_modbus_aio/client.py
tcp_modbus_aio/exceptions.py
tcp_modbus_aio/ping.py
tcp_modbus_aio/py.typed
tcp_modbus_aio/typed_functions.py
tcp_modbus_aio/utils.py
tcp_modbus_aio-0.4.7.dist-info/METADATA
tcp_modbus_aio-0.4.7.dist-info/WHEEL
tcp_modbus_aio-0.4.7.dist-info/entry_points.txt
tcp_modbus_aio-0.4.7.dist-info/licenses/LICENSE
tcp_modbus_aio-0.4.7.dist-info/RECORD
