Metadata-Version: 2.4
Name: tcp-modbus-aio
Version: 0.4.7
Summary: asyncio client library for tcp modbus devices
License: MIT
License-File: LICENSE
Author: Josh Gruenstein
Author-email: josh@tutorintelligence.com
Requires-Python: >=3.10,<4.0
Classifier: License :: OSI Approved :: MIT License
Classifier: Programming Language :: Python :: 3
Classifier: Programming Language :: Python :: 3.10
Classifier: Programming Language :: Python :: 3.11
Classifier: Programming Language :: Python :: 3.12
Classifier: Programming Language :: Python :: 3.13
Classifier: Programming Language :: Python :: 3.14
Requires-Dist: aiosocks (>=0.2.6,<0.3.0)
Requires-Dist: cachetools (>=5.3.3,<6.0.0)
Requires-Dist: types-cachetools (>=5.3.0.7,<6.0.0.0)
Requires-Dist: typing-extensions (>=4.11.0,<5.0.0)
Requires-Dist: umodbus (>=1.0.4,<2.0.0)
